flood_mapper/__init__.py
flood_mapper/flood_mapper.py
flood_mapper-0.1.2.dist-info/WHEEL
flood_mapper-0.1.2.dist-info/METADATA
flood_mapper-0.1.2.dist-info/RECORD
