Metadata-Version: 2.1
Name: flood-mapper
Version: 0.1.2
Summary: 
Home-page: https://github.com/cateseale/flood-mapper
License: MIT
Author: cate
Author-email: catherineseale@gmail.com
Requires-Python: >=3.6,<4.0
Classifier: License :: OSI Approved :: MIT License
Classifier: Programming Language :: Python :: 3
Classifier: Programming Language :: Python :: 3.6
Classifier: Programming Language :: Python :: 3.7
Classifier: Programming Language :: Python :: 3.8
Classifier: Programming Language :: Python :: 3.9
Requires-Dist: earthengine-api (>=0.1.288,<0.2.0)
Project-URL: Repository, https://github.com/cateseale/flood-mapper
